LICENSE
README.md
create_pyproject_toml
mypydie.py
requirements.txt
setup.cfg
mypydie-0.33.data/data/bin/LICENSE
mypydie-0.33.data/data/bin/create_pyproject_toml
mypydie-0.33.data/data/bin/mypydie.py
mypydie-0.33.data/data/bin/requirements.txt
mypydie-0.33.data/data/bin/setup.py
mypydie-0.33.dist-info/licenses/LICENSE
mypydie.egg-info/PKG-INFO
mypydie.egg-info/SOURCES.txt
mypydie.egg-info/dependency_links.txt
mypydie.egg-info/requires.txt
mypydie.egg-info/top_level.txt
mypydie-0.33.dist-info/METADATA
mypydie-0.33.dist-info/WHEEL
mypydie-0.33.dist-info/top_level.txt
mypydie-0.33.dist-info/RECORD
