Metadata-Version: 2.4
Name: mypydie
Version: 0.33
Summary: dier
Author: Norman Koch
Platform: Linux
License-File: LICENSE
Requires-Dist: wheel
Dynamic: author
Dynamic: description
Dynamic: description-content-type
Dynamic: license-file
Dynamic: platform
Dynamic: requires-dist
Dynamic: summary
